MANIFEST.in
README.rst
setup.py
django_nose2.egg-info/PKG-INFO
django_nose2.egg-info/SOURCES.txt
django_nose2.egg-info/dependency_links.txt
django_nose2.egg-info/requires.txt
django_nose2.egg-info/top_level.txt
djnose2/__init__.py
djnose2/runner.py