Metadata-Version: 1.0
Name: django-nose2
Version: 0.1.1
Summary: Test runner for django that runs tests with nose2
Home-page: https://github.com/jpellerin/django-nose2
Author: Jason Pellerin
Author-email: jpellerin+nose@gmail.com
License: UNKNOWN
Platform: UNKNOWN
